coards.py
setup.cfg
setup.py
coards.egg-info/PKG-INFO
coards.egg-info/SOURCES.txt
coards.egg-info/dependency_links.txt
coards.egg-info/entry_points.txt
coards.egg-info/top_level.txt
coards.egg-info/zip-safe
