Metadata-Version: 1.0
Name: coards
Version: 0.2.1
Summary: Convert COARDS time specification to a datetime object.
Home-page: http://dealmeida.net/projects/coards
Author: Roberto De Almeida
Author-email: rob@pydap.org
License: MIT
Download-URL: http://cheeseshop.python.org/packages/source/c/coards/coards-0.2.1.tar.gz
Keywords: data time coards netcdf
Platform: UNKNOWN
Classifier: Development Status :: 4 - Beta
Classifier: Environment :: Console
Classifier: Intended Audience :: Developers
Classifier: Intended Audience :: Science/Research
Classifier: License :: OSI Approved :: MIT License
Classifier: Operating System :: OS Independent
Classifier: Programming Language :: Python
Classifier: Topic :: Scientific/Engineering
Classifier: Topic :: Software Development :: Libraries :: Python Modules
